bin/__init__.py
bin/kudu
cairo-src/__init__.py
cairo-src/evm/__init__.py
cairo-src/evm/array.cairo
cairo-src/evm/bit_packing.cairo
cairo-src/evm/calls.cairo
cairo-src/evm/exec_env.cairo
cairo-src/evm/memory.cairo
cairo-src/evm/output.cairo
cairo-src/evm/sha3.cairo
cairo-src/evm/stack.cairo
cairo-src/evm/uint256.cairo
cairo-src/evm/utils.cairo
cli/StarkNetEvmContract.py
cli/__init__.py
cli/commands.py
cli/warp_cli.py
yul/AstMapper.py
yul/AstVisitor.py
yul/BuiltinHandler.py
yul/ExpressionSplitter.py
yul/ForLoopEliminator.py
yul/ForLoopSimplifier.py
yul/FunctionGenerator.py
yul/FunctionPruner.py
yul/Imports.py
yul/LeaveNormalizer.py
yul/MangleNamesVisitor.py
yul/NameGenerator.py
yul/RevertNormalizer.py
yul/Scope.py
yul/ScopeFlattener.py
yul/SwitchToIfVisitor.py
yul/ToCairoVisitor.py
yul/WarpException.py
yul/__init__.py
yul/call_graph.py
yul/extract_block.py
yul/implicits.py
yul/main.py
yul/parse.py
yul/storage_access.py
yul/top_sort.py
yul/utils.py
yul/yul_ast.py
evm_warp-0.2.2.dist-info/LICENSE
evm_warp-0.2.2.dist-info/METADATA
evm_warp-0.2.2.dist-info/WHEEL
evm_warp-0.2.2.dist-info/dependency_links.txt
evm_warp-0.2.2.dist-info/entry_points.txt
evm_warp-0.2.2.dist-info/top_level.txt
evm_warp-0.2.2.dist-info/RECORD
