Metadata-Version: 2.1
Name: evm-warp
Version: 0.2.2
Summary: Transpile EVM-Compatible Languages To Cairo
Home-page: https://github.com/NethermindEth/warp
Author: Nethermind
Author-email: hello@nethermind.io
License: Apache 2.0
Platform: UNKNOWN
Classifier: Programming Language :: Python :: 3.7
Classifier: License :: OSI Approved :: Apache Software License
Requires-Python: >=3.7
Requires-Dist: eth-hash (==0.2.0)
Requires-Dist: ecdsa
Requires-Dist: fastecdsa
Requires-Dist: sympy
Requires-Dist: pytest (==6.2.4)
Requires-Dist: pytest-parallel
Requires-Dist: py-solc-x (==1.1.0)
Requires-Dist: cairo-lang (==0.5.1)
Requires-Dist: aiohttp (<4,>=3.7.4)
Requires-Dist: eth-utils (<1.10)
Requires-Dist: click
Requires-Dist: lark
